gportal/__init__.py
gportal/data/datasets.json
gportal/dataset.py
gportal/file/__init__.py
gportal/file/gcomc.py
gportal/http_client.py
gportal/product.py
gportal/search.py
gportal/sftp.py
gportal-0.4.0.dist-info/LICENSE
gportal-0.4.0.dist-info/METADATA
gportal-0.4.0.dist-info/WHEEL
gportal-0.4.0.dist-info/RECORD
