Metadata-Version: 2.1
Name: gportal
Version: 0.4.0
Summary: Client for JAXA G-Portal Catalogue Service and SFTP
Home-page: https://github.com/sankichi92/gportal-python
License: MIT
Author: Takahiro Miyoshi
Author-email: takahiro-miyoshi@sankichi.net
Requires-Python: >=3.9,<4.0
Classifier: License :: OSI Approved :: MIT License
Classifier: Programming Language :: Python :: 3
Classifier: Programming Language :: Python :: 3.9
Classifier: Programming Language :: Python :: 3.10
Classifier: Programming Language :: Python :: 3.11
Provides-Extra: gcomc
Requires-Dist: h5py (>=3.8.0,<4.0.0) ; extra == "gcomc"
Requires-Dist: numpy (>=1.18,<2.0) ; extra == "gcomc"
Requires-Dist: paramiko (>=3.1.0,<4.0.0)
Requires-Dist: rasterio (>=1.3.6,<2.0.0) ; extra == "gcomc"
Requires-Dist: requests (>=2.28.2,<3.0.0)
Project-URL: Documentation, https://gportal.readthedocs.io/
Project-URL: Repository, https://github.com/sankichi92/gportal-python
